Metadata-Version: 2.1
Name: mrpautofaiss
Version: 2.17.0
Summary: # AutoFaiss
Home-page: https://github.com/criteo/autofaiss
Author: Criteo
Classifier: License :: OSI Approved :: Apache Software License
Classifier: Operating System :: OS Independent
Classifier: Programming Language :: Python :: 3
Classifier: Programming Language :: Python :: 3.6
Classifier: Programming Language :: Python :: 3.7
Classifier: Programming Language :: Python :: 3.8
Classifier: Programming Language :: Python :: 3.9
Classifier: Programming Language :: Python :: 3.10
Classifier: Programming Language :: Python :: 3.11
Classifier: Intended Audience :: Developers
License-File: LICENSE
Requires-Dist: dataclasses<1.0.0,>=0.6; python_version < "3.7"
Requires-Dist: fire<0.6.0,>=0.4.0
Requires-Dist: numpy<2,>=1.19.5
Requires-Dist: pandas<3,>=1.1.5
Requires-Dist: pyarrow<16,>=6.0.1
Requires-Dist: tqdm<5,>=4.62.3
Requires-Dist: faiss-cpu<1.7.3; python_version < "3.7"
Requires-Dist: faiss-cpu<2,>=1; python_version >= "3.7"
Requires-Dist: fsspec>=2022.1.0
Requires-Dist: embedding_reader<2,>=1.5.1
